keras_wc_embd/__init__.py
keras_wc_embd/word_char_embd.py
keras_word_char_embd-0.0.7.dist-info/DESCRIPTION.rst
keras_word_char_embd-0.0.7.dist-info/METADATA
keras_word_char_embd-0.0.7.dist-info/RECORD
keras_word_char_embd-0.0.7.dist-info/WHEEL
keras_word_char_embd-0.0.7.dist-info/metadata.json
keras_word_char_embd-0.0.7.dist-info/top_level.txt
