Metadata-Version: 2.0
Name: keras-word-char-embd
Version: 0.0.7
Summary: Concatenate word and character embeddings in Keras
Home-page: https://github.com/PoWWoP/keras_word_char_embd
Author: CyberZHG
Author-email: CyberZHG@gmail.com
License: LICENSE
Platform: UNKNOWN
Classifier: Programming Language :: Python :: 3
Classifier: License :: OSI Approved :: MIT License
Classifier: Operating System :: OS Independent
Requires-Dist: keras
